textmining_utility/__init__.py
textmining_utility/config.py
textmining_utility/lexicons.py
textmining_utility/text_miner.py
textmining_utility/tm_with_spacy.py
textmining_utility/topic_modeler.py
textmining_utility/utils.py
textmining_utility/annotator/__init__.py
textmining_utility/annotator/annotator.toml
textmining_utility/annotator/orchestrator.py
textmining_utility/annotator/registered_pipes.py
textmining_utility/annotator/instance/__init__.py
textmining_utility/annotator/instance/dummy.py
textmining_utility/annotator/instance/emotion_annotator.py
textmining_utility/annotator/instance/empath_annotator.py
textmining_utility/annotator/instance/hedge_orchestrator.py
textmining_utility/annotator/instance/ner_annotator.py
textmining_utility/annotator/instance/toxicity_orchestrator.py
textmining_utility/annotator/pipe/__init__.py
textmining_utility/annotator/pipe/linguistic/__init__.py
textmining_utility/annotator/pipe/linguistic/discourse_marker.py
textmining_utility/annotator/pipe/linguistic/emotion.py
textmining_utility/annotator/pipe/linguistic/empath.py
textmining_utility/annotator/pipe/linguistic/hedge.py
textmining_utility/annotator/pipe/linguistic/metadata.py
textmining_utility/annotator/pipe/linguistic/mpqa.py
textmining_utility/annotator/pipe/linguistic/toxicity.py
textmining_utility/annotator/pipe/linguistic/typos.py
textmining_utility/annotator/pipeline/__init__.py
textmining_utility/annotator/pipeline/pipeline_base.py
textmining_utility/corpus-analytics-logs/logs.txt
textmining_utility-0.5.dist-info/LICENSE
textmining_utility-0.5.dist-info/WHEEL
textmining_utility-0.5.dist-info/METADATA
textmining_utility-0.5.dist-info/RECORD
